together_worker/common.py
together_worker/fast_inference.py
together_worker/fast_training.py
together_worker/runner.py
together_worker/serving.py
together_worker-0.1.22.dist-info/METADATA
together_worker-0.1.22.dist-info/WHEEL
together_worker-0.1.22.dist-info/RECORD
